romatch/__init__.py
romatch/benchmarks/__init__.py
romatch/benchmarks/hpatches_sequences_homog_benchmark.py
romatch/benchmarks/megadepth_dense_benchmark.py
romatch/benchmarks/megadepth_pose_estimation_benchmark.py
romatch/benchmarks/megadepth_pose_estimation_benchmark_poselib.py
romatch/benchmarks/scannet_benchmark.py
romatch/checkpointing/__init__.py
romatch/checkpointing/checkpoint.py
romatch/datasets/__init__.py
romatch/datasets/megadepth.py
romatch/datasets/scannet.py
romatch/losses/__init__.py
romatch/losses/robust_loss.py
romatch/losses/robust_loss_tiny_roma.py
romatch/models/__init__.py
romatch/models/encoders.py
romatch/models/matcher.py
romatch/models/tiny.py
romatch/models/model_zoo/__init__.py
romatch/models/model_zoo/roma_models.py
romatch/models/transformer/__init__.py
romatch/models/transformer/dinov2.py
romatch/models/transformer/layers/__init__.py
romatch/models/transformer/layers/attention.py
romatch/models/transformer/layers/block.py
romatch/models/transformer/layers/dino_head.py
romatch/models/transformer/layers/drop_path.py
romatch/models/transformer/layers/layer_scale.py
romatch/models/transformer/layers/mlp.py
romatch/models/transformer/layers/patch_embed.py
romatch/models/transformer/layers/swiglu_ffn.py
romatch/train/__init__.py
romatch/train/train.py
romatch/utils/__init__.py
romatch/utils/kde.py
romatch/utils/local_correlation.py
romatch/utils/transforms.py
romatch/utils/utils.py
romatch_roicat-0.1.1.dist-info/licenses/LICENSE
romatch_roicat-0.1.1.dist-info/METADATA
romatch_roicat-0.1.1.dist-info/WHEEL
romatch_roicat-0.1.1.dist-info/top_level.txt
romatch_roicat-0.1.1.dist-info/RECORD
