Metadata-Version: 2.4
Name: romatch_roicat
Version: 0.1.1
Author: Johan Edstedt
License-File: LICENSE
Requires-Dist: torch
Requires-Dist: einops
Requires-Dist: torchvision
Requires-Dist: opencv-contrib-python-headless
Requires-Dist: kornia
Requires-Dist: loguru
Requires-Dist: tqdm
Requires-Dist: matplotlib
Requires-Dist: h5py
Requires-Dist: wandb
Requires-Dist: timm
Requires-Dist: poselib
Dynamic: author
Dynamic: description
Dynamic: description-content-type
Dynamic: license-file
Dynamic: requires-dist
